<?xml version="1.0" encoding="UTF-8"?>
<!DOCTYPE mapper PUBLIC "-//mybatis.org//DTD Mapper 3.0//EN" "http://mybatis.org/dtd/mybatis-3-mapper.dtd">
<mapper namespace="com.lanou.mapper.OwnerMapper">
	<resultMap id="BaseResultMap" type="com.lanou.entity.Owner">
		<!-- WARNING - @mbg.generated This element is automatically generated by 
			MyBatis Generator, do not modify. This element was generated on Tue Dec 26 
			10:20:04 CST 2017. -->
		<id column="id" jdbcType="INTEGER" property="id" />
		<result column="name" jdbcType="VARCHAR" property="name" />
		<result column="idCard" jdbcType="VARCHAR" property="idCard" />
		<result column="sex" jdbcType="VARCHAR" property="sex" />
		<result column="tel" jdbcType="VARCHAR" property="tel" />
		<result column="housing_estate_code" jdbcType="VARCHAR"
			property="housing_estate_code" />
		<result column="address" jdbcType="VARCHAR" property="address" />
		<result column="score" jdbcType="INTEGER" property="score" />
		<result column="openid" jdbcType="VARCHAR" property="openid" />
		<result column="create_time" jdbcType="TIMESTAMP" property="create_time" />
	</resultMap>
	<resultMap id="selectMap" type="com.lanou.bean.OwnerBean">
		<!-- WARNING - @mbg.generated This element is automatically generated by 
			MyBatis Generator, do not modify. This element was generated on Tue Dec 26 
			10:20:04 CST 2017. -->
		<id column="id" jdbcType="INTEGER" property="id" />
		<result column="name" jdbcType="VARCHAR" property="name" />
		<result column="sex" jdbcType="VARCHAR" property="sex" />
		<result column="tel" jdbcType="VARCHAR" property="tel" />
		<result column="housing_estate" jdbcType="VARCHAR" property="housing_estate" />
		<result column="address" jdbcType="VARCHAR" property="address" />
		<result column="score" jdbcType="INTEGER" property="score" />
		<result column="openid" jdbcType="VARCHAR" property="openid" />
		<result column="create_time" jdbcType="TIMESTAMP" property="create_time" />
	</resultMap>
	<sql id="Base_Column_List">
		<!-- WARNING - @mbg.generated This element is automatically generated by 
			MyBatis Generator, do not modify. This element was generated on Tue Dec 26 
			10:20:04 CST 2017. -->
		id, name, idCard, sex, tel, housing_estate_code, address, score,
		openid, create_time
	</sql>
	<select id="selectByPrimaryKey" parameterType="java.lang.Integer"
		resultMap="BaseResultMap">
		<!-- WARNING - @mbg.generated This element is automatically generated by 
			MyBatis Generator, do not modify. This element was generated on Tue Dec 26 
			10:20:04 CST 2017. -->
		select
		<include refid="Base_Column_List" />
		from owner
		where id = #{id,jdbcType=INTEGER}
	</select>
	<!-- 查询业主的信息 -->
	<select id="selectAll" resultMap="selectMap">
		<!-- WARNING - @mbg.generated This element is automatically generated by 
			MyBatis Generator, do not modify. This element was generated on Tue Dec 26 
			10:20:04 CST 2017. -->
		SELECT t.id ,t.name,t.sex,t.tel,t1.`name` as
		housing_estate,t.address,t.score,t.openid,t.create_time FROM owner t
		LEFT JOIN housing_estate t1 on t.housing_estate_code=t1.`code`
		where
		1=1
		<if test="username!=null and username!='' ">
			and t.name like concat('%',#{username},'%')
		</if>
		order by ${column} ${order}
		limit #{start},#{length}
	</select>
	<!-- 查询总的页数 -->
	<select id="selectCount" resultType="java.lang.Integer">
		select count(t.id) FROM owner t
		LEFT JOIN housing_estate t1 on
		t.housing_estate_code=t1.`code`
		where 1=1
		<if test="username!=null and username!='' ">
			and t.name like concat('%',#{username},'%')
		</if>
	</select>
	<delete id="deleteByPrimaryKey" parameterType="java.lang.Integer">
		<!-- WARNING - @mbg.generated This element is automatically generated by 
			MyBatis Generator, do not modify. This element was generated on Tue Dec 26 
			10:20:04 CST 2017. -->
		delete from owner
		where id = #{id,jdbcType=INTEGER}
	</delete>
	<insert id="insert" parameterType="com.lanou.entity.Owner">
		<!-- WARNING - @mbg.generated This element is automatically generated by 
			MyBatis Generator, do not modify. This element was generated on Tue Dec 26 
			10:20:04 CST 2017. -->
		insert into owner (id, name, idCard,
		sex, tel, housing_estate_code,
		address, score, openid,
		create_time)
		values (#{id,jdbcType=INTEGER},
		#{name,jdbcType=VARCHAR},
		#{idCard,jdbcType=VARCHAR},
		#{sex,jdbcType=VARCHAR}, #{tel,jdbcType=VARCHAR},
		#{housing_estate_code,jdbcType=VARCHAR},
		#{address,jdbcType=VARCHAR},
		#{score,jdbcType=INTEGER},
		#{openid,jdbcType=VARCHAR},
		#{create_time,jdbcType=TIMESTAMP})
	</insert>
	<insert id="insertSelective" parameterType="com.lanou.entity.Owner">
		<!-- WARNING - @mbg.generated This element is automatically generated by 
			MyBatis Generator, do not modify. This element was generated on Tue Dec 26 
			10:20:04 CST 2017. -->
		insert into owner
		<trim prefix="(" suffix=")" suffixOverrides=",">
			<if test="id != null">
				id,
			</if>
			<if test="name != null">
				name,
			</if>
			<if test="idCard != null">
				idCard,
			</if>
			<if test="sex != null">
				sex,
			</if>
			<if test="tel != null">
				tel,
			</if>
			<if test="housing_estate_code != null">
				housing_estate_code,
			</if>
			<if test="address != null">
				address,
			</if>
			<if test="score != null">
				score,
			</if>
			<if test="openid != null">
				openid,
			</if>
			<if test="create_time != null">
				create_time,
			</if>
		</trim>
		<trim prefix="values (" suffix=")" suffixOverrides=",">
			<if test="id != null">
				#{id,jdbcType=INTEGER},
			</if>
			<if test="name != null">
				#{name,jdbcType=VARCHAR},
			</if>
			<if test="idCard != null">
				#{idCard,jdbcType=VARCHAR},
			</if>
			<if test="sex != null">
				#{sex,jdbcType=VARCHAR},
			</if>
			<if test="tel != null">
				#{tel,jdbcType=VARCHAR},
			</if>
			<if test="housing_estate_code != null">
				#{housing_estate_code,jdbcType=VARCHAR},
			</if>
			<if test="address != null">
				#{address,jdbcType=VARCHAR},
			</if>
			<if test="score != null">
				#{score,jdbcType=INTEGER},
			</if>
			<if test="openid != null">
				#{openid,jdbcType=VARCHAR},
			</if>
			<if test="create_time != null">
				#{create_time,jdbcType=TIMESTAMP},
			</if>
		</trim>
	</insert>
	<update id="updateByPrimaryKeySelective" parameterType="com.lanou.entity.Owner">
		<!-- WARNING - @mbg.generated This element is automatically generated by 
			MyBatis Generator, do not modify. This element was generated on Tue Dec 26 
			10:20:04 CST 2017. -->
		update owner
		<set>
			<if test="name != null">
				name = #{name,jdbcType=VARCHAR},
			</if>
			<if test="idCard != null">
				idCard = #{idCard,jdbcType=VARCHAR},
			</if>
			<if test="sex != null">
				sex = #{sex,jdbcType=VARCHAR},
			</if>
			<if test="tel != null">
				tel = #{tel,jdbcType=VARCHAR},
			</if>
			<if test="housing_estate_code != null">
				housing_estate_code =
				#{housing_estate_code,jdbcType=VARCHAR},
			</if>
			<if test="address != null">
				address = #{address,jdbcType=VARCHAR},
			</if>
			<if test="score != null">
				score = #{score,jdbcType=INTEGER},
			</if>
			<if test="openid != null">
				openid = #{openid,jdbcType=VARCHAR},
			</if>
			<if test="create_time != null">
				create_time = #{create_time,jdbcType=TIMESTAMP},
			</if>
		</set>
		where id = #{id,jdbcType=INTEGER}
	</update>
	<update id="updateByPrimaryKey" parameterType="com.lanou.entity.Owner">
		<!-- WARNING - @mbg.generated This element is automatically generated by 
			MyBatis Generator, do not modify. This element was generated on Tue Dec 26 
			10:20:04 CST 2017. -->
		update owner
		set name = #{name,jdbcType=VARCHAR},
		idCard =
		#{idCard,jdbcType=VARCHAR},
		sex = #{sex,jdbcType=VARCHAR},
		tel =
		#{tel,jdbcType=VARCHAR},
		housing_estate_code =
		#{housing_estate_code,jdbcType=VARCHAR},
		address =
		#{address,jdbcType=VARCHAR},
		score = #{score,jdbcType=INTEGER},
		openid =
		#{openid,jdbcType=VARCHAR},
		create_time =
		#{create_time,jdbcType=TIMESTAMP}
		where id = #{id,jdbcType=INTEGER}
	</update>
</mapper>